LICENSE
MANIFEST.in
README.rst
requirements.txt
setup.py
.github/workflows/main.yml
.github/workflows/pypi.yml
pysalsa.egg-info/PKG-INFO
pysalsa.egg-info/SOURCES.txt
pysalsa.egg-info/dependency_links.txt
pysalsa.egg-info/entry_points.txt
pysalsa.egg-info/not-zip-safe
pysalsa.egg-info/requires.txt
pysalsa.egg-info/top_level.txt
salsa/__init__.py
salsa/scripts/__init__.py
salsa/scripts/compute_ttest.py
salsa/scripts/main.py