Metadata-Version: 2.1
Name: pysalsa
Version: 0.1.0
Summary: convert between bioinformatics formats
Author: The biomics Contributors
Author-email: thomas.cokelaer@pasteur.fr
Maintainer: Thomas Cokelaer
Maintainer-email: thomas.cokelaer@pasteur.fr
License: BSD
Keywords: NGS
Platform: Linux
Platform: Unix
Platform: MacOsX
Platform: Windows
Classifier: Development Status :: 4 - Beta
Classifier: Intended Audience :: Developers
Classifier: Intended Audience :: Science/Research
Classifier: License :: OSI Approved :: BSD License
Classifier: Operating System :: OS Independent
Classifier: Programming Language :: Python :: 3.6
Classifier: Programming Language :: Python :: 3.7
Classifier: Programming Language :: Python :: 3.8
Classifier: Programming Language :: Python :: 3.9
Classifier: Topic :: Software Development :: Libraries :: Python Modules
Classifier: Topic :: Scientific/Engineering :: Bio-Informatics
Classifier: Topic :: Scientific/Engineering :: Information Analysis
Provides-Extra: testing
License-File: LICENSE
